{
  "logoType": "default",
  "logo": {
    "lucideIcon": "",
    "imagePath": "",
    "imageLink": ""
  },
  "logoScale": 1.2,
  "iconColorType": "default",
  "wordmark": "Obsidian",
  "customFont": "interfaceFont",
  "fontSize": "4em",
  "fontColorType": "default",
  "fontWeight": 600,
  "maxResults": 5,
  "showbookmarkedFiles": true,
  "showRecentFiles": false,
  "maxRecentFiles": 5,
  "storeRecentFile": true,
  "showPath": true,
  "selectionHighlight": "default",
  "showShortcuts": true,
  "markdownOnly": false,
  "unresolvedLinks": false,
  "recentFilesStore": [
    {
      "filepath": "博客/Obsidian/Obsidian 达人成长之路 #4：使用 Text expand 插件插入查询结果.md",
      "timestamp": 1717335010183
    },
    {
      "filepath": "博客/Obsidian/Obsidian 达人成长之路 #3：使用终极工具 Dataview 释放笔记库的潜力 · 案例讲解.md",
      "timestamp": 1717334996487
    },
    {
      "filepath": "博客/Obsidian/Obsidian 达人成长之路：QuickAdd 插件使用.md",
      "timestamp": 1717252028583
    },
    {
      "filepath": "博客/Obsidian/Obsidian 达人成长之路：Tasks 插件助你实现高效任务规划与执行.md",
      "timestamp": 1717217775878
    }
  ],
  "bookmarkedFileStore": [],
  "searchDelay": 0,
  "replaceNewTabs": true,
  "newTabOnStart": false,
  "closePreviousSessionTabs": false,
  "omnisearch": false,
  "showOmnisearchExcerpt": true,
  "showStarredFiles": false,
  "starredFileStore": []
}